#![allow(dead_code)]

pub const BYTECODE_JAVA_LE_4: u8 = 48;
pub const BYTECODE_JAVA_5: u8 = 49;
pub const BYTECODE_JAVA_6: u8 = 50;
pub const BYTECODE_JAVA_7: u8 = 51;
pub const BYTECODE_JAVA_8: u8 = 52;
pub const BYTECODE_JAVA_9: u8 = 53;
pub const BYTECODE_JAVA_10: u8 = 54;
pub const BYTECODE_JAVA_11: u8 = 55;
pub const BYTECODE_JAVA_12: u8 = 56;
pub const BYTECODE_JAVA_13: u8 = 57;
pub const BYTECODE_JAVA_14: u8 = 58;
pub const BYTECODE_JAVA_15: u8 = 59;
pub const BYTECODE_JAVA_16: u8 = 60;
pub const BYTECODE_JAVA_17: u8 = 61;

pub const TYPE_BYTE: u8 = 0;
pub const TYPE_CHAR: u8 = 1;
pub const TYPE_DOUBLE: u8 = 2;
pub const TYPE_FLOAT: u8 = 3;
pub const TYPE_INT: u8 = 4;
pub const TYPE_LONG: u8 = 5;
pub const TYPE_SHORT: u8 = 6;
pub const TYPE_BOOLEAN: u8 = 7;
pub const TYPE_OBJECT: u8 = 8;
pub const TYPE_ADDRESS: u8 = 9;
pub const TYPE_VOID: u8 = 10;
pub const TYPE_ANY: u8 = 11;
pub const TYPE_GROUP2EMPTY: u8 = 12;
pub const TYPE_NULL: u8 = 13;
pub const TYPE_NOTINITIALIZED: u8 = 14;
pub const TYPE_BYTECHAR: u8 = 15;
pub const TYPE_SHORTCHAR: u8 = 16;
pub const TYPE_UNKNOWN: u8 = 17;
pub const TYPE_GENVAR: u8 = 18;
pub const TYPE_FAMILY_UNKNOWN: u8 = 0;
pub const TYPE_FAMILY_BOOLEAN: u8 = 1;
pub const TYPE_FAMILY_INTEGER: u8 = 2;
pub const TYPE_FAMILY_FLOAT: u8 = 3;
pub const TYPE_FAMILY_LONG: u8 = 4;
pub const TYPE_FAMILY_DOUBLE: u8 = 5;
pub const TYPE_FAMILY_OBJECT: u8 = 6;


pub const ACC_PUBLIC: u16 = 0x0001;
pub const ACC_PRIVATE: u16 = 0x0002;
pub const ACC_PROTECTED: u16 = 0x0004;
pub const ACC_STATIC: u16 = 0x0008;
pub const ACC_FINAL: u16 = 0x0010;
pub const ACC_SYNCHRONIZED: u8 = 0x0020;
pub const ACC_OPEN: u16 = 0x0020;
pub const ACC_NATIVE: u16 = 0x0100;
pub const ACC_ABSTRACT: u16 = 0x0400;
pub const ACC_STRICT: u16 = 0x0800;
pub const ACC_VOLATILE: u16 = 0x0040;
pub const ACC_BRIDGE: u16 = 0x0040;
pub const ACC_TRANSIENT: u16 = 0x0080;
pub const ACC_VARARGS: u16 = 0x0080;
pub const ACC_SYNTHETIC: u16 = 0x1000;
pub const ACC_ANNOTATION: u16 = 0x2000;
pub const ACC_ENUM: u16 = 0x4000;
pub const ACC_MANDATED: u16 = 0x8000;
pub const ACC_MODULE: u16 = 0x8000;
pub const ACC_SUPER: u16 = 0x0020;
pub const ACC_INTERFACE: u16 = 0x0200;

#[derive(Debug, Clone)]
pub struct AccessFlags(pub u16);

impl AccessFlags {
    pub fn contains(&self, flag: u16) -> bool {
        self.0.clone() & flag == flag
    }
}


pub const GROUP_GENERAL: u8 = 1;
pub const GROUP_JUMP: u8 = 2;
pub const GROUP_SWITCH: u8 = 3;
pub const GROUP_INVOCATION: u8 = 4;
pub const GROUP_FIELDACCESS: u8 = 5;
pub const GROUP_RETURN: u8 = 6;


pub const CONSTANT_UTF8: u8 = 1;
pub const CONSTANT_INTEGER: u8 = 3;
pub const CONSTANT_FLOAT: u8 = 4;
pub const CONSTANT_LONG: u8 = 5;
pub const CONSTANT_DOUBLE: u8 = 6;
pub const CONSTANT_CLASS: u8 = 7;
pub const CONSTANT_STRING: u8 = 8;
pub const CONSTANT_FIELDREF: u8 = 9;
pub const CONSTANT_METHODREF: u8 = 10;
pub const CONSTANT_INTERFACE_METHODREF: u8 = 11;
pub const CONSTANT_NAME_AND_TYPE: u8 = 12;
pub const CONSTANT_METHOD_HANDLE: u8 = 15;
pub const CONSTANT_METHOD_TYPE: u8 = 16;
pub const CONSTANT_DYNAMIC: u8 = 17;
pub const CONSTANT_INVOKE_DYNAMIC: u8 = 18;
pub const CONSTANT_MODULE: u8 = 19;
pub const CONSTANT_PACKAGE: u8 = 20;


pub const CONSTANT_METHOD_HANDLE_REF_GET_FIELD: u8 = 1;
pub const CONSTANT_METHOD_HANDLE_REF_GET_STATIC: u8 = 2;
pub const CONSTANT_METHOD_HANDLE_REF_PUT_FIELD: u8 = 3;
pub const CONSTANT_METHOD_HANDLE_REF_PUT_STATIC: u8 = 4;
pub const CONSTANT_METHOD_HANDLE_REF_INVOKE_VIRTUAL: u8 = 5;
pub const CONSTANT_METHOD_HANDLE_REF_INVOKE_STATIC: u8 = 6;
pub const CONSTANT_METHOD_HANDLE_REF_INVOKE_SPECIAL: u8 = 7;
pub const CONSTANT_METHOD_HANDLE_REF_NEW_INVOKE_SPECIAL: u8 = 8;
pub const CONSTANT_METHOD_HANDLE_REF_INVOKE_INTERFACE: u8 = 9;

pub const OPC_NOP: u8 = 0;
pub const OPC_ACONST_NULL: u8 = 1;
pub const OPC_ICONST_M1: u8 = 2;
pub const OPC_ICONST_0: u8 = 3;
pub const OPC_ICONST_1: u8 = 4;
pub const OPC_ICONST_2: u8 = 5;
pub const OPC_ICONST_3: u8 = 6;
pub const OPC_ICONST_4: u8 = 7;
pub const OPC_ICONST_5: u8 = 8;
pub const OPC_LCONST_0: u8 = 9;
pub const OPC_LCONST_1: u8 = 10;
pub const OPC_FCONST_0: u8 = 11;
pub const OPC_FCONST_1: u8 = 12;
pub const OPC_FCONST_2: u8 = 13;
pub const OPC_DCONST_0: u8 = 14;
pub const OPC_DCONST_1: u8 = 15;
pub const OPC_BIPUSH: u8 = 16;
pub const OPC_SIPUSH: u8 = 17;
pub const OPC_LDC: u8 = 18;
pub const OPC_LDC_W: u8 = 19;
pub const OPC_LDC2_W: u8 = 20;
pub const OPC_ILOAD: u8 = 21;
pub const OPC_LLOAD: u8 = 22;
pub const OPC_FLOAD: u8 = 23;
pub const OPC_DLOAD: u8 = 24;
pub const OPC_ALOAD: u8 = 25;
pub const OPC_ILOAD_0: u8 = 26;
pub const OPC_ILOAD_1: u8 = 27;
pub const OPC_ILOAD_2: u8 = 28;
pub const OPC_ILOAD_3: u8 = 29;
pub const OPC_LLOAD_0: u8 = 30;
pub const OPC_LLOAD_1: u8 = 31;
pub const OPC_LLOAD_2: u8 = 32;
pub const OPC_LLOAD_3: u8 = 33;
pub const OPC_FLOAD_0: u8 = 34;
pub const OPC_FLOAD_1: u8 = 35;
pub const OPC_FLOAD_2: u8 = 36;
pub const OPC_FLOAD_3: u8 = 37;
pub const OPC_DLOAD_0: u8 = 38;
pub const OPC_DLOAD_1: u8 = 39;
pub const OPC_DLOAD_2: u8 = 40;
pub const OPC_DLOAD_3: u8 = 41;
pub const OPC_ALOAD_0: u8 = 42;
pub const OPC_ALOAD_1: u8 = 43;
pub const OPC_ALOAD_2: u8 = 44;
pub const OPC_ALOAD_3: u8 = 45;
pub const OPC_IALOAD: u8 = 46;
pub const OPC_LALOAD: u8 = 47;
pub const OPC_FALOAD: u8 = 48;
pub const OPC_DALOAD: u8 = 49;
pub const OPC_AALOAD: u8 = 50;
pub const OPC_BALOAD: u8 = 51;
pub const OPC_CALOAD: u8 = 52;
pub const OPC_SALOAD: u8 = 53;
pub const OPC_ISTORE: u8 = 54;
pub const OPC_LSTORE: u8 = 55;
pub const OPC_FSTORE: u8 = 56;
pub const OPC_DSTORE: u8 = 57;
pub const OPC_ASTORE: u8 = 58;
pub const OPC_ISTORE_0: u8 = 59;
pub const OPC_ISTORE_1: u8 = 60;
pub const OPC_ISTORE_2: u8 = 61;
pub const OPC_ISTORE_3: u8 = 62;
pub const OPC_LSTORE_0: u8 = 63;
pub const OPC_LSTORE_1: u8 = 64;
pub const OPC_LSTORE_2: u8 = 65;
pub const OPC_LSTORE_3: u8 = 66;
pub const OPC_FSTORE_0: u8 = 67;
pub const OPC_FSTORE_1: u8 = 68;
pub const OPC_FSTORE_2: u8 = 69;
pub const OPC_FSTORE_3: u8 = 70;
pub const OPC_DSTORE_0: u8 = 71;
pub const OPC_DSTORE_1: u8 = 72;
pub const OPC_DSTORE_2: u8 = 73;
pub const OPC_DSTORE_3: u8 = 74;
pub const OPC_ASTORE_0: u8 = 75;
pub const OPC_ASTORE_1: u8 = 76;
pub const OPC_ASTORE_2: u8 = 77;
pub const OPC_ASTORE_3: u8 = 78;
pub const OPC_IASTORE: u8 = 79;
pub const OPC_LASTORE: u8 = 80;
pub const OPC_FASTORE: u8 = 81;
pub const OPC_DASTORE: u8 = 82;
pub const OPC_AASTORE: u8 = 83;
pub const OPC_BASTORE: u8 = 84;
pub const OPC_CASTORE: u8 = 85;
pub const OPC_SASTORE: u8 = 86;
pub const OPC_POP: u8 = 87;
pub const OPC_POP2: u8 = 88;
pub const OPC_DUP: u8 = 89;
pub const OPC_DUP_X1: u8 = 90;
pub const OPC_DUP_X2: u8 = 91;
pub const OPC_DUP2: u8 = 92;
pub const OPC_DUP2_X1: u8 = 93;
pub const OPC_DUP2_X2: u8 = 94;
pub const OPC_SWAP: u8 = 95;
pub const OPC_IADD: u8 = 96;
pub const OPC_LADD: u8 = 97;
pub const OPC_FADD: u8 = 98;
pub const OPC_DADD: u8 = 99;
pub const OPC_ISUB: u8 = 100;
pub const OPC_LSUB: u8 = 101;
pub const OPC_FSUB: u8 = 102;
pub const OPC_DSUB: u8 = 103;
pub const OPC_IMUL: u8 = 104;
pub const OPC_LMUL: u8 = 105;
pub const OPC_FMUL: u8 = 106;
pub const OPC_DMUL: u8 = 107;
pub const OPC_IDIV: u8 = 108;
pub const OPC_LDIV: u8 = 109;
pub const OPC_FDIV: u8 = 110;
pub const OPC_DDIV: u8 = 111;
pub const OPC_IREM: u8 = 112;
pub const OPC_LREM: u8 = 113;
pub const OPC_FREM: u8 = 114;
pub const OPC_DREM: u8 = 115;
pub const OPC_INEG: u8 = 116;
pub const OPC_LNEG: u8 = 117;
pub const OPC_FNEG: u8 = 118;
pub const OPC_DNEG: u8 = 119;
pub const OPC_ISHL: u8 = 120;
pub const OPC_LSHL: u8 = 121;
pub const OPC_ISHR: u8 = 122;
pub const OPC_LSHR: u8 = 123;
pub const OPC_IUSHR: u8 = 124;
pub const OPC_LUSHR: u8 = 125;
pub const OPC_IAND: u8 = 126;
pub const OPC_LAND: u8 = 127;
pub const OPC_IOR: u8 = 128;
pub const OPC_LOR: u8 = 129;
pub const OPC_IXOR: u8 = 130;
pub const OPC_LXOR: u8 = 131;
pub const OPC_IINC: u8 = 132;
pub const OPC_I2L: u8 = 133;
pub const OPC_I2F: u8 = 134;
pub const OPC_I2D: u8 = 135;
pub const OPC_L2I: u8 = 136;
pub const OPC_L2F: u8 = 137;
pub const OPC_L2D: u8 = 138;
pub const OPC_F2I: u8 = 139;
pub const OPC_F2L: u8 = 140;
pub const OPC_F2D: u8 = 141;
pub const OPC_D2I: u8 = 142;
pub const OPC_D2L: u8 = 143;
pub const OPC_D2F: u8 = 144;
pub const OPC_I2B: u8 = 145;
pub const OPC_I2C: u8 = 146;
pub const OPC_I2S: u8 = 147;
pub const OPC_LCMP: u8 = 148;
pub const OPC_FCMPL: u8 = 149;
pub const OPC_FCMPG: u8 = 150;
pub const OPC_DCMPL: u8 = 151;
pub const OPC_DCMPG: u8 = 152;
pub const OPC_IFEQ: u8 = 153;
pub const OPC_IFNE: u8 = 154;
pub const OPC_IFLT: u8 = 155;
pub const OPC_IFGE: u8 = 156;
pub const OPC_IFGT: u8 = 157;
pub const OPC_IFLE: u8 = 158;
pub const OPC_IF_ICMPEQ: u8 = 159;
pub const OPC_IF_ICMPNE: u8 = 160;
pub const OPC_IF_ICMPLT: u8 = 161;
pub const OPC_IF_ICMPGE: u8 = 162;
pub const OPC_IF_ICMPGT: u8 = 163;
pub const OPC_IF_ICMPLE: u8 = 164;
pub const OPC_IF_ACMPEQ: u8 = 165;
pub const OPC_IF_ACMPNE: u8 = 166;
pub const OPC_GOTO: u8 = 167;
pub const OPC_JSR: u8 = 168;
pub const OPC_RET: u8 = 169;
pub const OPC_TABLESWITCH: u8 = 170;
pub const OPC_LOOKUPSWITCH: u8 = 171;
pub const OPC_IRETURN: u8 = 172;
pub const OPC_LRETURN: u8 = 173;
pub const OPC_FRETURN: u8 = 174;
pub const OPC_DRETURN: u8 = 175;
pub const OPC_ARETURN: u8 = 176;
pub const OPC_RETURN: u8 = 177;
pub const OPC_GETSTATIC: u8 = 178;
pub const OPC_PUTSTATIC: u8 = 179;
pub const OPC_GETFIELD: u8 = 180;
pub const OPC_PUTFIELD: u8 = 181;
pub const OPC_INVOKEVIRTUAL: u8 = 182;
pub const OPC_INVOKESPECIAL: u8 = 183;
pub const OPC_INVOKESTATIC: u8 = 184;
pub const OPC_INVOKEINTERFACE: u8 = 185;
pub const OPC_INVOKEDYNAMIC: u8 = 186;
pub const OPC_NEW: u8 = 187;
pub const OPC_NEWARRAY: u8 = 188;
pub const OPC_ANEWARRAY: u8 = 189;
pub const OPC_ARRAYLENGTH: u8 = 190;
pub const OPC_ATHROW: u8 = 191;
pub const OPC_CHECKCAST: u8 = 192;
pub const OPC_INSTANCEOF: u8 = 193;
pub const OPC_MONITORENTER: u8 = 194;
pub const OPC_MONITOREXIT: u8 = 195;
pub const OPC_WIDE: u8 = 196;
pub const OPC_MULTIANEWARRAY: u8 = 197;
pub const OPC_IFNULL: u8 = 198;
pub const OPC_IFNONNULL: u8 = 199;
pub const OPC_GOTO_W: u8 = 200;
pub const OPC_JSR_W: u8 = 201;

pub const CLINIT_NAME: &str = "<clinit>";
pub const INIT_NAME: &str = "<init>";